[
  {
    "name": "latest",
    "version": "1.0.0a1.dev19+gf1bb527",
    "url": "https://opencompes.github.io/docs/sed/latest"
  },
  {
    "name": "stable",
    "version": "0.4.1",
    "url": "https://opencompes.github.io/docs/sed/v0.4.1",
    "preferred": "true"
  },
  {
    "name": "develop",
    "version": "1.0.0a1.dev18+g8b76c82",
    "url": "https://opencompes.github.io/docs/sed/develop"
  },
  {
    "name": "v0.3.1",
    "version": "0.3.1",
    "url": "https://opencompes.github.io/docs/sed/v0.3.1"
  },
  {
    "name": "v0.3.2",
    "version": "0.3.2",
    "url": "https://opencompes.github.io/docs/sed/v0.3.2"
  },
  {
    "name": "v0.4.0",
    "version": "0.4.0",
    "url": "https://opencompes.github.io/docs/sed/v0.4.0"
  },
  {
    "name": "v1.0.0a0",
    "version": "1.0.0a0",
    "url": "https://opencompes.github.io/docs/sed/v1.0.0.a0"
  },
  {
    "name": "v0.4.1",
    "version": "0.4.1",
    "url": "https://opencompes.github.io/docs/sed/v0.4.1"
  }
]